kuksa/__init__.py
kuksa/val/__init__.py
kuksa/val/v1/__init__.py
kuksa/val/v1/types_pb2.py
kuksa/val/v1/types_pb2_grpc.py
kuksa/val/v1/val_pb2.py
kuksa/val/v1/val_pb2_grpc.py
kuksa/val/v2/__init__.py
kuksa/val/v2/types_pb2.py
kuksa/val/v2/types_pb2_grpc.py
kuksa/val/v2/val_pb2.py
kuksa/val/v2/val_pb2_grpc.py
kuksa_client/__init__.py
kuksa_client/__main__.py
kuksa_client/_metadata.py
kuksa_client/logo
kuksa_client/cli_backend/__init__.py
kuksa_client/cli_backend/grpc.py
kuksa_client/cli_backend/ws.py
kuksa_client/grpc/__init__.py
kuksa_client/grpc/aio.py
kuksa_client/kuksa_logger/__init__.py
kuksa_client/ws/__init__.py
kuksa_client-0.5.0.dist-info/licenses/LICENSE
sdv/__init__.py
sdv/databroker/__init__.py
sdv/databroker/v1/__init__.py
sdv/databroker/v1/broker_pb2.py
sdv/databroker/v1/broker_pb2_grpc.py
sdv/databroker/v1/collector_pb2.py
sdv/databroker/v1/collector_pb2_grpc.py
sdv/databroker/v1/types_pb2.py
sdv/databroker/v1/types_pb2_grpc.py
tests/__init__.py
tests/conftest.py
tests/test_basevssclient.py
tests/test_datapoint.py
tests/test_grpc.py
kuksa_client-0.5.0.dist-info/METADATA
kuksa_client-0.5.0.dist-info/WHEEL
kuksa_client-0.5.0.dist-info/entry_points.txt
kuksa_client-0.5.0.dist-info/top_level.txt
kuksa_client-0.5.0.dist-info/RECORD
