Metadata-Version: 2.4
Name: kuksa_client
Version: 0.5.0
Summary: KUKSA Python Client and SDK
Home-page: https://github.com/eclipse-kuksa/kuksa-python-sdk
Author: Eclipse KUKSA Project
Author-email: kuksa-dev@eclipse.org
Project-URL: Source, https://github.com/eclipse-kuksa/kuksa-python-sdk
Project-URL: Bug Tracker, https://github.com/eclipse-kuksa/kuksa-python-sdk/issues
Classifier: Intended Audience :: Developers
Classifier: Development Status :: 5 - Production/Stable
Classifier: Environment :: Console
Classifier: Programming Language :: Python :: 3
Classifier: License :: OSI Approved :: Apache Software License
Classifier: Operating System :: OS Independent
Classifier: Topic :: Software Development
Requires-Python: >=3.8
License-File: LICENSE
Requires-Dist: websockets>=10.1
Requires-Dist: cmd2<2.0,>=1.4
Requires-Dist: pygments>=2.15
Requires-Dist: grpcio-tools==1.68.0
Requires-Dist: jsonpath-ng>=1.5.3
Provides-Extra: test
Requires-Dist: pylint; extra == "test"
Requires-Dist: pytest; extra == "test"
Requires-Dist: pytest-asyncio; extra == "test"
Requires-Dist: pytest-cov; extra == "test"
Requires-Dist: pytest-mock; extra == "test"
Requires-Dist: pytest-timeout; extra == "test"
Dynamic: license-file
